ndspy/__init__.py
ndspy/_common.py
ndspy/_lzCommon.py
ndspy/bmg.py
ndspy/bnbl.py
ndspy/bncl.py
ndspy/code.py
ndspy/codeCompression.py
ndspy/color.py
ndspy/fnt.py
ndspy/graphics2D.py
ndspy/lz10.py
ndspy/model.py
ndspy/narc.py
ndspy/py.typed
ndspy/rom.py
ndspy/soundArchive.py
ndspy/soundBank.py
ndspy/soundGroup.py
ndspy/soundSequence.py
ndspy/soundSequenceArchive.py
ndspy/soundSequencePlayer.py
ndspy/soundStream.py
ndspy/soundStreamPlayer.py
ndspy/soundWave.py
ndspy/soundWaveArchive.py
ndspy/texture.py
ndspy/extras/__init__.py
ndspy/extras/_imageTexeler.py
ndspy/extras/music.py
ndspy/extras/soundEffect.py
ndspy/extras/textureEncoding.py
ndspy/extras/wbmgt/__init__.py
ndspy/extras/wbmgt/_common.py
ndspy/extras/wbmgt/_load.py
ndspy/extras/wbmgt/_save.py
ndspy-4.2.0.dist-info/LICENSE
ndspy-4.2.0.dist-info/METADATA
ndspy-4.2.0.dist-info/WHEEL
ndspy-4.2.0.dist-info/entry_points.txt
ndspy-4.2.0.dist-info/top_level.txt
ndspy-4.2.0.dist-info/RECORD
