Metadata-Version: 2.1
Name: ndspy
Version: 4.2.0
Summary: Python library that can help you read, modify and create many types of files used in Nintendo DS games.
Home-page: https://github.com/RoadrunnerWMC/ndspy
Author: RoadrunnerWMC
Author-email: roadrunnerwmc@gmail.com
License: UNKNOWN
Platform: UNKNOWN
Classifier: Programming Language :: Python :: 3.7
Classifier: Programming Language :: Python :: 3.8
Classifier: Programming Language :: Python :: 3.9
Classifier: Programming Language :: Python :: 3.10
Classifier: Programming Language :: Python :: 3.11
Classifier: Programming Language :: Python :: 3.12
Classifier: License :: OSI Approved :: GNU General Public License v3 or later (GPLv3+)
Classifier: Operating System :: OS Independent
Requires-Python: >=3.7
Provides-Extra: test
License-File: LICENSE
